spartan/__init__.py
spartan/main.py
spartan/services/__init__.py
spartan/services/application.py
spartan/services/comprehend.py
spartan/services/config.py
spartan/services/debug.py
spartan/services/deployment.py
spartan/services/ecs.py
spartan/services/handler/__init__.py
spartan/services/handler/aws_handler.py
spartan/services/handler/base.py
spartan/services/handler/gcp_handler.py
spartan/services/handler.py
spartan/services/infrastructure.py
spartan/services/job.py
spartan/services/layer.py
spartan/services/logs.py
spartan/services/migrate.py
spartan/services/model.py
spartan/services/motivate.py
spartan/services/notebook.py
spartan/services/parquet.py
spartan/services/request.py
spartan/services/response.py
spartan/services/route.py
spartan/services/s3.py
spartan/services/service.py
spartan/services/test.py
spartan/services/workflow/__init__.py
spartan/services/workflow/aws_workflow.py
spartan/services/workflow/base.py
spartan/services/workflow/gcp_workflow.py
spartan/services/workflow.py
spartan/stubs/debug/fastapi.stub
spartan/stubs/debug/module.stub
spartan/stubs/debug/python_file.stub
spartan/stubs/debug/python_file_with_arguments.stub
spartan/stubs/handler/alexa_skill_kit_subscribe.stub
spartan/stubs/handler/amazon_appsync_subsribe.stub
spartan/stubs/handler/amazon_kinesis_subscribe.stub
spartan/stubs/handler/amazon_lex_subscribe.stub
spartan/stubs/handler/amazon_mq_subscribe.stub
spartan/stubs/handler/amazon_msk_subscribe.stub
spartan/stubs/handler/amazon_redshift_subscribe.stub
spartan/stubs/handler/amazon_timestream_subscribe.stub
spartan/stubs/handler/api_subscribe.stub
spartan/stubs/handler/aws_codecommit_subscribe.stub
spartan/stubs/handler/aws_config_subscribe.stub
spartan/stubs/handler/aws_iot_button_subscribe.stub
spartan/stubs/handler/aws_iot_core_subscribe.stub
spartan/stubs/handler/aws_secrets_manager_rotation_subscribe.stub
spartan/stubs/handler/aws_step_function_subscribe.stub
spartan/stubs/handler/cloudtrail_subscribe.stub
python_spartan-0.3.9.dist-info/LICENSE
python_spartan-0.3.9.dist-info/METADATA
python_spartan-0.3.9.dist-info/WHEEL
python_spartan-0.3.9.dist-info/entry_points.txt
python_spartan-0.3.9.dist-info/RECORD
