Metadata-Version: 2.1
Name: python-spartan
Version: 0.3.9
Summary: Spartan, often referred to as "The swiss army knife for serverless development," is a tool that simplifies the creation of serverless applications on popular cloud providers by generating Python code for classes and more. It streamlines your development process, saving you time and ensuring code consistency in your serverless projects.
Author: nerdmonkey
Author-email: sydel.palinlin@gmail.com
Requires-Python: >=3.11,<4.0
Classifier: Development Status :: 4 - Beta
Classifier: Intended Audience :: Developers
Classifier: License :: OSI Approved :: MIT License
Classifier: Programming Language :: Python :: 3
Classifier: Programming Language :: Python :: 3.11
Classifier: Programming Language :: Python :: 3.12
Classifier: Programming Language :: Python :: 3.13
Classifier: Programming Language :: Python :: 3 :: Only
Classifier: Topic :: Internet :: WWW/HTTP :: Dynamic Content
Classifier: Topic :: Software Development :: Libraries :: Python Modules
Classifier: Topic :: System :: Systems Administration
Requires-Dist: alembic (>=1.12.0,<2.0.0)
Requires-Dist: boto3 (>=1.34.0,<2.0.0)
Requires-Dist: click (==8.1.7)
Requires-Dist: google-cloud (>=0.34.0,<0.35.0)
Requires-Dist: google-cloud-functions (>=1.21.0,<2.0.0)
Requires-Dist: google-cloud-storage (>=3.7.0,<4.0.0)
Requires-Dist: google-cloud-workflows (>=1.16.0,<2.0.0)
Requires-Dist: inflect (>=7.2.1,<8.0.0)
Requires-Dist: pandas (>=2.3.1,<3.0.0)
Requires-Dist: poetry (>=1.7.0,<2.0.0)
Requires-Dist: pre-commit (>=4.2.0,<5.0.0)
Requires-Dist: pyarrow (>=21.0.0,<22.0.0)
Requires-Dist: pymysql (>=1.1.0,<2.0.0)
Requires-Dist: pytest (>=8.3.2,<9.0.0)
Requires-Dist: pytest-coverage (>=0.0,<0.1)
Requires-Dist: pyyaml (>=6.0.1,<7.0.0)
Requires-Dist: requests (>=2.31.0,<3.0.0)
Requires-Dist: rich (>=14.0.0,<15.0.0)
Requires-Dist: typer (==0.12.3)
